pynta/__init__.py
pynta/__main__.py
pynta/config.py
pynta/controller/__init__.py
pynta/controller/data_sources/__init__.py
pynta/controller/devices/__init__.py
pynta/controller/devices/arduino/__init__.py
pynta/controller/devices/arduino/arduino.py
pynta/controller/devices/hamamatsu/__init__.py
pynta/controller/devices/hamamatsu/hamamatsu_camera.py
pynta/controller/devices/keysight/__init__.py
pynta/controller/devices/keysight/infiniivision.py
pynta/controller/devices/photonicscience/__init__.py
pynta/controller/devices/photonicscience/scmoscam.py
pynta/exceptions/__init__.py
pynta/exceptions/exceptions.py
pynta/model/__init__.py
pynta/model/exceptions.py
pynta/model/cameras/__init__.py
pynta/model/cameras/base_camera.py
pynta/model/cameras/basler.py
pynta/model/cameras/decorators.py
pynta/model/cameras/dummy_camera.py
pynta/model/cameras/exceptions.py
pynta/model/cameras/hamamatsu.py
pynta/model/cameras/psi.py
pynta/model/cameras/simulate_brownian.py
pynta/model/daqs/NI.py
pynta/model/daqs/__init__.py
pynta/model/daqs/daq_dummy.py
pynta/model/daqs/skeleton.py
pynta/model/experiment/__init__.py
pynta/model/experiment/base_experiment.py
pynta/model/experiment/config.py
pynta/model/experiment/publisher.py
pynta/model/experiment/subscriber.py
pynta/model/experiment/dispertech/__init__.py
pynta/model/experiment/dispertech/database.py
pynta/model/experiment/dispertech/fiber_tracking.py
pynta/model/experiment/dispertech/util.py
pynta/model/experiment/nanoparticle_tracking/__init__.py
pynta/model/experiment/nanoparticle_tracking/decorators.py
pynta/model/experiment/nanoparticle_tracking/exceptions.py
pynta/model/experiment/nanoparticle_tracking/localization.py
pynta/model/experiment/nanoparticle_tracking/motor_test.py
pynta/model/experiment/nanoparticle_tracking/np_tracking.py
pynta/model/experiment/nanoparticle_tracking/saver.py
pynta/model/experiment/nanoparticle_tracking/waterfall_worker.py
pynta/tests/__init__.py
pynta/tests/test_controllers.py
PyNTA-0.1.4.dist-info/AUTHORS
PyNTA-0.1.4.dist-info/LICENSE
PyNTA-0.1.4.dist-info/METADATA
PyNTA-0.1.4.dist-info/WHEEL
PyNTA-0.1.4.dist-info/entry_points.txt
PyNTA-0.1.4.dist-info/top_level.txt
PyNTA-0.1.4.dist-info/RECORD
