Metadata-Version: 2.1
Name: PyNTA
Version: 0.1.4
Summary: Python Nanoparticle Tracking Analysis
Home-page: https://github.com/nanoepics/pynta
Author: Aquiles Carattino
Author-email: aquiles@uetke.com
License: GPLv3
Platform: UNKNOWN
Classifier: Intended Audience :: End Users/Desktop
Classifier: Operating System :: Microsoft :: Windows
Classifier: Programming Language :: Python
Requires-Dist: pyqt5
Requires-Dist: numpy
Requires-Dist: pyqtgraph
Requires-Dist: pint
Requires-Dist: h5py
Requires-Dist: trackpy
Requires-Dist: pandas
Requires-Dist: pyyaml
Requires-Dist: pyzmq
Requires-Dist: numba
